setup.py
raresim/__init__.py
raresim/__main__.py
raresim/cli.py
raresim/calculate/__init__.py
raresim/calculate/expected_vars.py
raresim/common/__init__.py
raresim/common/bins.py
raresim/common/exceptions.py
raresim/common/legend.py
raresim/common/sparse.py
raresim/engine/__init__.py
raresim/engine/config.py
raresim/engine/pruners.py
raresim/engine/runner.py
raresim/engine/utils.py
raresim-3.0.0.dist-info/licenses/LICENSE
tests/__init__.py
tests/conftest.py
tests/get_expected_values.py
tests/test_bins.py
tests/test_config.py
tests/test_exceptions.py
tests/test_expected_vars.py
tests/test_integration.py
tests/test_legend.py
tests/test_pruners.py
tests/test_real_data_integration.py
tests/test_sparse.py
tests/test_utils.py
raresim-3.0.0.dist-info/METADATA
raresim-3.0.0.dist-info/WHEEL
raresim-3.0.0.dist-info/entry_points.txt
raresim-3.0.0.dist-info/top_level.txt
raresim-3.0.0.dist-info/RECORD
